peko/__init__.py
peko/peko.py
peko-0.0.0.1.dist-info/LICENSE
peko-0.0.0.1.dist-info/METADATA
peko-0.0.0.1.dist-info/WHEEL
peko-0.0.0.1.dist-info/top_level.txt
peko-0.0.0.1.dist-info/RECORD
