Metadata-Version: 2.1
Name: peko
Version: 0.0.0.1
Summary: Enrique Coronado
Home-page: http://enriquecoronadozu.github.io
Author: Enrique Coronado
Author-email: enriquecoronadozu@gmail.com
Keywords: Robotics
Classifier: Development Status :: 4 - Beta
Classifier: Programming Language :: Python :: 2.7
Classifier: Programming Language :: Python :: 3
Classifier: Programming Language :: Python :: 3.6
Classifier: Programming Language :: Python :: 3.7
Classifier: Programming Language :: Python :: 3.8
Classifier: Programming Language :: Python :: 3.9
Classifier: License :: OSI Approved :: BSD License
Classifier: Intended Audience :: Developers
Classifier: Intended Audience :: Other Audience
Classifier: Intended Audience :: Science/Research
Classifier: Intended Audience :: Education
Classifier: Topic :: Text Processing
Classifier: Operating System :: Microsoft :: Windows
Classifier: Operating System :: OS Independent
License-File: LICENSE
